google_calendar_analytics/__init__.py
google_calendar_analytics/_version.py
google_calendar_analytics/analytics.py
google_calendar_analytics/authentication/__init__.py
google_calendar_analytics/authentication/auth.py
google_calendar_analytics/collecting/__init__.py
google_calendar_analytics/collecting/collector.py
google_calendar_analytics/core/__init__.py
google_calendar_analytics/core/exceptions.py
google_calendar_analytics/processing/__init__.py
google_calendar_analytics/processing/transformer.py
google_calendar_analytics/visualization/__init__.py
google_calendar_analytics/visualization/image_saver.py
google_calendar_analytics/visualization/visual_design.py
google_calendar_analytics/visualization/visualizer_factory.py
google_calendar_analytics-0.5.0.dist-info/LICENSE
google_calendar_analytics-0.5.0.dist-info/METADATA
google_calendar_analytics-0.5.0.dist-info/WHEEL
google_calendar_analytics-0.5.0.dist-info/RECORD
