Metadata-Version: 2.1
Name: google-calendar-analytics
Version: 0.5.0
Summary: A Python library for analyzing Google Calendar data.
License: MIT
Keywords: google,calendar,analytics,data analysis,event tracking,attendee tracking
Author: Berupor
Author-email: evgeniy.zelenoff@gmail.com
Requires-Python: >=3.11,<4.0
Classifier: Development Status :: 4 - Beta
Classifier: Intended Audience :: Developers
Classifier: License :: OSI Approved :: MIT License
Classifier: Operating System :: OS Independent
Classifier: Programming Language :: Python :: 3
Classifier: Programming Language :: Python :: 3.11
Classifier: Programming Language :: Python :: 3.10
Classifier: Topic :: Scientific/Engineering :: Information Analysis
Requires-Dist: aiohttp (==3.8.4)
Requires-Dist: certifi (==2022.12.7)
Requires-Dist: google-api-python-client (==2.77.0)
Requires-Dist: google-auth (==2.16.0)
Requires-Dist: google-auth-httplib2 (==0.1.0)
Requires-Dist: google-auth-oauthlib (==1.0.0)
Requires-Dist: kaleido (==0.2.1)
Requires-Dist: pandas (==1.5.3)
Requires-Dist: plotly (==5.13.0)
